AUTHORS
ChangeLog
LICENSE
MANIFEST.in
README.rst
requirements.txt
setup.cfg
setup.py
benchmark_dashboard/__init__.py
benchmark_dashboard/dashboard.py
benchmark_dashboard/models.py
benchmark_dashboard/api/__init__.py
benchmark_dashboard/api/loader.py
benchmark_dashboard/api/db/__init__.py
benchmark_dashboard/api/db/base.py
benchmark_dashboard/api/db/deployments.py
benchmark_dashboard/api/db/tasks.py
benchmark_dashboard/deployments/__init__.py
benchmark_dashboard/deployments/forms.py
benchmark_dashboard/deployments/panel.py
benchmark_dashboard/deployments/tables.py
benchmark_dashboard/deployments/urls.py
benchmark_dashboard/deployments/views.py
benchmark_dashboard/deployments/templates/deployments/index.html
benchmark_dashboard/static/benchmark/css/report.css
benchmark_dashboard/static/benchmark/js/report.js
benchmark_dashboard/tasks/__init__.py
benchmark_dashboard/tasks/forms.py
benchmark_dashboard/tasks/panel.py
benchmark_dashboard/tasks/tables.py
benchmark_dashboard/tasks/urls.py
benchmark_dashboard/tasks/utils.py
benchmark_dashboard/tasks/views.py
benchmark_dashboard/tasks/templates/tasks/_create.html
benchmark_dashboard/tasks/templates/tasks/_select.html
benchmark_dashboard/tasks/templates/tasks/base.mako
benchmark_dashboard/tasks/templates/tasks/create.html
benchmark_dashboard/tasks/templates/tasks/detail.html
benchmark_dashboard/tasks/templates/tasks/index.html
benchmark_dashboard/tasks/templates/tasks/report.mako
benchmark_dashboard/tasks/templates/tasks/select.html
benchmark_dashboard/utils/__init__.py
benchmark_dashboard/utils/async.py
benchmark_dashboard/utils/rally.py
benchmark_dashboard/utils/widgets.py
debian/_99_benchmark.py
debian/changelog
debian/compat
debian/control
debian/copyright
debian/docs
debian/install
debian/postinst
debian/postrm
debian/rules
debian/source/format
debian/source/options
horizon_benchmark_dashboard.egg-info/PKG-INFO
horizon_benchmark_dashboard.egg-info/SOURCES.txt
horizon_benchmark_dashboard.egg-info/dependency_links.txt
horizon_benchmark_dashboard.egg-info/not-zip-safe
horizon_benchmark_dashboard.egg-info/pbr.json
horizon_benchmark_dashboard.egg-info/requires.txt
horizon_benchmark_dashboard.egg-info/top_level.txt